tdnpathviz/__init__.py
tdnpathviz/clustering.py
tdnpathviz/datasets.py
tdnpathviz/hierarchy_exploration.py
tdnpathviz/utils.py
tdnpathviz/visualizations.py
tdnpathviz/data/train_dataset.csv
tdnpathviz/npathwidget/__init__.py
tdnpathviz/npathwidget/icicle_chart_plotter.py
tdnpathviz/npathwidget/loadinbar.gif
tdnpathviz/npathwidget/npath_query.py
tdnpathviz/npathwidget/sankey_chart_plotter.py
tdnpathviz/npathwidget/utils.py
tdnpathviz/npathwidget/widget_app.py
tdnpathviz/npathwidget/widget_callables.py
tdnpathviz/npathwidget/widget_layout.py
tdnpathviz-0.1.3.2.dist-info/METADATA
tdnpathviz-0.1.3.2.dist-info/WHEEL
tdnpathviz-0.1.3.2.dist-info/top_level.txt
tdnpathviz-0.1.3.2.dist-info/RECORD
