Metadata-Version: 2.1
Name: tdnpathviz
Version: 0.1.3.2
Summary: A python package to visualize npath outputs in python and much more ...
Author: Denis Molin
Requires-Python: >=3.6
Requires-Dist: teradataml>=20.0.0.0
Requires-Dist: tqdm
Requires-Dist: pandas
Requires-Dist: numpy
Requires-Dist: plotly
Requires-Dist: matplotlib
Requires-Dist: seaborn
Requires-Dist: opencv-python
Requires-Dist: Pillow
Requires-Dist: ipywidgets
Requires-Dist: IPython
